{
  "meetings": [
    {
      "id": 1,
      "title": "BoardGames for everyone",
      "description": "Learn how to play various boardgames",
      "date": "25 January 2022"
    },
    {
      "id": 2,
      "title": "Become a ninja in vue ",
      "description": "Master the framwork vue.js",
      "date": "12 February 2022"
    },
    {
      "id": 3,
      "title": "Box like a champion",
      "description": "Learn the basics and more of boxing",
      "date": "2 June 2022"
    },
    {
      "description": "Delicious Toast",
      "title": "Toast",
      "category": "",
      "id": "e4e4649f-27cd-4287-bdf9-a10897496389",
      "date": "Tomorrow",
      "organizer": "Gome Jabar"
    },
    {
      "description": "",
      "title": "(*,..,*)",
      "category": "",
      "id": "5da94ddf-7ed2-4f24-9eeb-004ea2b69ce8",
      "date": "?_?",
      "organizer": "Gome Jabar"
    }
  ]
}